simplexfmrartifact/__init__.py
simplexfmrartifact/simpletransformers.py
simplexfmrartifact-0.0.13.dist-info/METADATA
simplexfmrartifact-0.0.13.dist-info/WHEEL
simplexfmrartifact-0.0.13.dist-info/top_level.txt
simplexfmrartifact-0.0.13.dist-info/RECORD
