Metadata-Version: 2.1
Name: simplexfmrartifact
Version: 0.0.13
Summary: BentoML artifact framework for simpletransformers
Home-page: https://github.com/markmo/simplexfmrartifact
Author: Mark Moloney
Author-email: m4rkmo@gmail.com
License: UNKNOWN
Platform: UNKNOWN
Classifier: Programming Language :: Python :: 3
Classifier: License :: OSI Approved :: MIT License
Classifier: Operating System :: OS Independent
Requires-Python: >=3.6
Requires-Dist: BentoML (==0.10.1)
